<?xml version="1.0" encoding="UTF-8"?>
<!DOCTYPE plist PUBLIC "-//Apple//DTD PLIST 1.0//EN" "http://www.apple.com/DTDs/PropertyList-1.0.dtd">
<plist version="1.0">
<dict>
	<key>author</key>
	<string></string>
	<key>comments</key>
	<string></string>
	<key>isUsingConstrainedLayout</key>
	<false/>
	<key>keywords</key>
	<string></string>
	<key>mindMap</key>
	<dict>
		<key>associations</key>
		<array/>
		<key>color</key>
		<string>{0.492, 0.609, 0.778, 1.000}</string>
		<key>mainNodes</key>
		<array>
			<dict>
				<key>contentAlignment</key>
				<integer>1</integer>
				<key>fillColor</key>
				<string>{1.000, 1.000, 1.000, 1.000}</string>
				<key>isDecreasingBranchThickness</key>
				<true/>
				<key>isDrawingFill</key>
				<true/>
				<key>isLeftAligned</key>
				<false/>
				<key>location</key>
				<string>{-358.08984375, -102.953125}</string>
				<key>nodeID</key>
				<string>95093016-D5A6-4002-AD01-1A5DFD768611</string>
				<key>strokeColor</key>
				<string>{0.500, 0.500, 0.500, 1.000}</string>
				<key>strokeStyle</key>
				<integer>0</integer>
				<key>strokeWidth</key>
				<real>2</real>
				<key>subnodes</key>
				<array>
					<dict>
						<key>contentAlignment</key>
						<integer>1</integer>
						<key>fillColor</key>
						<string>{1.000, 1.000, 1.000, 1.000}</string>
						<key>isDecreasingBranchThickness</key>
						<true/>
						<key>isDrawingFill</key>
						<false/>
						<key>isLeftAligned</key>
						<false/>
						<key>location</key>
						<string>{-196.08984375, -193.953125}</string>
						<key>nodeID</key>
						<string>5A56A254-CAD4-49C0-8A7C-ACAEC8A1C03A</string>
						<key>strokeColor</key>
						<string>{1.000, 0.800, 0.400, 1.000}</string>
						<key>strokeStyle</key>
						<integer>0</integer>
						<key>strokeWidth</key>
						<real>6</real>
						<key>subnodes</key>
						<array>
							<dict>
								<key>contentAlignment</key>
								<integer>1</integer>
								<key>fillColor</key>
								<string>{1.000, 1.000, 1.000, 1.000}</string>
								<key>isDecreasingBranchThickness</key>
								<true/>
								<key>isDrawingFill</key>
								<false/>
								<key>isLeftAligned</key>
								<false/>
								<key>location</key>
								<string>{-62.08984375, -193.953125}</string>
								<key>nodeID</key>
								<string>BEBC6209-393D-4C93-9C5E-F731EF9694DD</string>
								<key>strokeColor</key>
								<string>{1.000, 0.800, 0.400, 1.000}</string>
								<key>strokeStyle</key>
								<integer>0</integer>
								<key>strokeWidth</key>
								<real>5</real>
								<key>subnodes</key>
								<array/>
								<key>title</key>
								<dict>
									<key>attributedText</key>
									<data>
								YnBsaXN0MDDU
								AQIDBAUG5OVY
								JHZlcnNpb25Y
								JG9iamVjdHNZ
								JGFyY2hpdmVy
								VCR0b3ASAAGG
								oK8QLQcIDxAX
								ICEiIycxODxA
								SElndn1+goeM
								kZaboKWqr7S5
								vL2+wsrL19jZ
								2tvc4FUkbnVs
								bNMJCgsMDQ5W
								c3RyaW5nWmF0
								dHJpYnV0ZXNW
								JGNsYXNzgAKA
								A4AsXVdyaXRl
								ICggTkFLICnS
								EQsSFlpOUy5v
								YmplY3RzoxMU
								FYAEgA2AI4Af
								0xgRCxkcH1dO
								Uy5rZXlzohob
								gAWABqIdHoAH
								gAiADF8QJGtN
								TkF0dHJpYnV0
								ZWRTdHJpbmdB
								dHRyaWJ1dGVS
								YW5nZUtleV8Q
								KGtNTkF0dHJp
								YnV0ZWRTdHJp
								bmdBdHRyaWJ1
								dGVBdHRyaWJ1
								dGVLZXlXezAs
								IDEzfdIkCyUm
								VWNvbG9ygAmA
								C9ULKCkqKywt
								Li8wU3JlZFVh
								bHBoYVRibHVl
								VWdyZWVugAoi
								AAAAACI/gAAA
								IgAAAAAiAAAA
								ANIyMzQ1WiRj
								bGFzc25hbWVY
								JGNsYXNzZXNY
								TU5DQ29sb3Ki
								NjdYTU5DQ29s
								b3JYTlNPYmpl
								Y3TSMjM5Ol8Q
								E01OQVNGb3Jl
								Z3JvdW5kQ29s
								b3KiOzdfEBNN
								TkFTRm9yZWdy
								b3VuZENvbG9y
								0jIzPT5fEBNO
								U011dGFibGVE
								aWN0aW9uYXJ5
								oz0/N1xOU0Rp
								Y3Rpb25hcnnT
								GBELQUQfohob
								gAWABqJFRoAO
								gA+ADFd7MCwg
								MTN93xAPSktM
								TU4LT1BRUlNU
								VVZXWFlaW1xd
								Xl9gYWJjZGVm
								XxARbWF4aW11
								bUxpbmVIZWln
								aHRYdGFiU3Rv
								cHNfEBBwYXJh
								Z3JhcGhTcGFj
								aW5nWmhlYWRJ
								bmRlbnRdbGlu
								ZUJyZWFrTW9k
								ZVtsaW5lU3Bh
								Y2luZ1lhbGln
								bm1lbnRadGFp
								bEluZGVudF8Q
								EW1pbmltdW1M
								aW5lSGVpZ2h0
								XxAWcGFyYWdy
								YXBoU3BhY2lu
								Z0JlZm9yZV8Q
								EmRlZmF1bHRU
								YWJJbnRlcnZh
								bF8QEmZpcnN0
								TGluZUhlYWRJ
								ZGVudF8QFGJh
								c2VXcml0aW5n
								RGlyZWN0aW9u
								XxASbGluZUhl
								aWdodE11bHRp
								cGxlIgAAAACA
								ECIAAAAAIgAA
								AACAEoAiIgAA
								AACAICIAAAAA
								IgAAAAAiAAAA
								ACIAAAAAIgAA
								AACAISIAAAAA
								0hELaBasaWpr
								bG1ub3BxcnN0
								gBGAFIAVgBaA
								F4AYgBmAGoAb
								gByAHYAegB/U
								UHd4C1x6e3xX
								b3B0aW9uc1hs
								b2NhdGlvboAS
								gAAiQeAAAIAT
								EADSMjN/gFtN
								TkFTVGV4dFRh
								YqKBN1tNTkFT
								VGV4dFRhYtRQ
								d3gLXHqFfIAS
								gAAiQmAAAIAT
								1FB3eAtceop8
								gBKAACJCqAAA
								gBPUUHd4C1x6
								j3yAEoAAIkLg
								AACAE9RQd3gL
								XHqUfIASgAAi
								QwwAAIAT1FB3
								eAtcepl8gBKA
								ACJDKAAAgBPU
								UHd4C1x6nnyA
								EoAAIkNEAACA
								E9RQd3gLXHqj
								fIASgAAiQ2AA
								AIAT1FB3eAtc
								eqh8gBKAACJD
								fAAAgBPUUHd4
								C1x6rXyAEoAA
								IkOMAACAE9RQ
								d3gLXHqyfIAS
								gAAiQ5oAAIAT
								1FB3eAtcerd8
								gBKAACJDqAAA
								gBPSMjO6u1dO
								U0FycmF5oro3
								EAQUAAAAAAAA
								AAD/////////
								/9IyM7/AXxAT
								TU5BU1BhcmFn
								cmFwaHlTdHls
								ZaLBN18QE01O
								QVNQYXJhZ3Jh
								cGh5U3R5bGXT
								GBELw8Yfohob
								gAWABqLHyIAk
								gCWADFd7MCwg
								MTN91szNzs/Q
								C9HS09TV1lRz
								aXplWGZvbnRO
								YW1lWWV4cGFu
								c2lvbltvYmxp
								cXVlbmVzc18Q
								EmJhc2VsaW5l
								QWRqdXN0bWVu
								dIAngCaAKoAp
								gCiAK1xMdWNp
								ZGFHcmFuZGUi
								QUAAACIAAAAA
								IgAAAAAiAAAA
								ANIyM93eWE1O
								QVNGb250ot83
								WE1OQVNGb250
								0jIz4eJfEBNN
								TkNBdHRyaWJ1
								dGVkU3RyaW5n
								ouM3XxATTU5D
								QXR0cmlidXRl
								ZFN0cmluZ18Q
								D05TS2V5ZWRB
								cmNoaXZlctHm
								518QEU1OQzBk
								ZXJSb290T2Jq
								ZWN0gAEACAAR
								ABoAIwAtADIA
								NwBnAG0AdAB7
								AIYAjQCPAJEA
								kwChAKYAsQC1
								ALcAuQC7AL0A
								xADMAM8A0QDT
								ANYA2ADaANwB
								AwEuATYBOwFB
								AUMBRQFQAVQB
								WgFfAWUBZwFs
								AXEBdgF7AYAB
								iwGUAZ0BoAGp
								AbIBtwHNAdAB
								5gHrAgECBQIS
								AhkCHAIeAiAC
								IwIlAicCKQIx
								AlICZgJvAoIC
								jQKbAqcCsQK8
								AtAC6QL+AxMD
								KgM/A0QDRgNL
								A1ADUgNUA1kD
								WwNgA2UDagNv
								A3QDdgN7A4AD
								jQOPA5EDkwOV
								A5cDmQObA50D
								nwOhA6MDpQOn
								A7ADuAPBA8MD
								xQPKA8wDzgPT
								A98D4gPuA/cD
								+QP7BAAEAgQL
								BA0EDwQUBBYE
								HwQhBCMEKAQq
								BDMENQQ3BDwE
								PgRHBEkESwRQ
								BFIEWwRdBF8E
								ZARmBG8EcQRz
								BHgEegSDBIUE
								hwSMBI4ElwSZ
								BJsEoASiBKsE
								rQSvBLQEtgS/
								BMEEwwTIBMoE
								zwTXBNoE3ATt
								BPIFCAULBSEF
								KAUrBS0FLwUy
								BTQFNgU4BUAF
								TQVSBVsFZQVx
								BYYFiAWKBYwF
								jgWQBZIFnwWk
								BakFrgWzBbgF
								wQXEBc0F0gXo
								BesGAQYTBhYG
								KgAAAAAAAAIB
								AAAAAAAAAOgA
								AAAAAAAAAAAA
								AAAAAAYs
									</data>
									<key>constrainedWidth</key>
									<integer>300</integer>
									<key>shrinkToFitContent</key>
									<integer>1</integer>
									<key>text</key>
									<string>{\rtf1\ansi\ansicpg1252\cocoartf1187
{\fonttbl\f0\fnil\fcharset0 LucidaGrande;}
{\colortbl;\red255\green255\blue255;}
\pard\tx560\tx1120\tx1680\tx2240\tx2800\tx3360\tx3920\tx4480\tx5040\tx5600\tx6160\tx6720\pardirnatural

\f0\fs24 \cf0 Write ( NAK )}</string>
								</dict>
							</dict>
							<dict>
								<key>contentAlignment</key>
								<integer>1</integer>
								<key>fillColor</key>
								<string>{1.000, 1.000, 1.000, 1.000}</string>
								<key>isDecreasingBranchThickness</key>
								<true/>
								<key>isDrawingFill</key>
								<false/>
								<key>isLeftAligned</key>
								<false/>
								<key>location</key>
								<string>{-62.08984375, -134.953125}</string>
								<key>nodeID</key>
								<string>58174560-F2F5-42B0-80EA-D4E04D93ADCD</string>
								<key>strokeColor</key>
								<string>{1.000, 0.800, 0.400, 1.000}</string>
								<key>strokeStyle</key>
								<integer>0</integer>
								<key>strokeWidth</key>
								<real>5</real>
								<key>subnodes</key>
								<array/>
								<key>title</key>
								<dict>
									<key>attributedText</key>
									<data>
								YnBsaXN0MDDU
								AQIDBAUG5OVY
								JHZlcnNpb25Y
								JG9iamVjdHNZ
								JGFyY2hpdmVy
								VCR0b3ASAAGG
								oK8QLQcIDxAX
								ICEiIycxODxA
								SElndn1+goeM
								kZaboKWqr7S5
								vL2+wsrL19jZ
								2tvc4FUkbnVs
								bNMJCgsMDQ5W
								c3RyaW5nWmF0
								dHJpYnV0ZXNW
								JGNsYXNzgAKA
								A4AsXxAbQ29u
								dG9sbGVyOjpQ
								bGF5SW5pdFNl
								cXVlbmNl0hEL
								EhZaTlMub2Jq
								ZWN0c6MTFBWA
								BIANgCOAH9MY
								EQsZHB9XTlMu
								a2V5c6IaG4AF
								gAaiHR6AB4AI
								gAxfECRrTU5B
								dHRyaWJ1dGVk
								U3RyaW5nQXR0
								cmlidXRlUmFu
								Z2VLZXlfEChr
								TU5BdHRyaWJ1
								dGVkU3RyaW5n
								QXR0cmlidXRl
								QXR0cmlidXRl
								S2V5V3swLCAy
								N33SJAslJlVj
								b2xvcoAJgAvV
								CygpKissLS4v
								MFNyZWRVYWxw
								aGFUYmx1ZVVn
								cmVlboAKIgAA
								AAAiP4AAACIA
								AAAAIgAAAADS
								MjM0NVokY2xh
								c3NuYW1lWCRj
								bGFzc2VzWE1O
								Q0NvbG9yojY3
								WE1OQ0NvbG9y
								WE5TT2JqZWN0
								0jIzOTpfEBNN
								TkFTRm9yZWdy
								b3VuZENvbG9y
								ojs3XxATTU5B
								U0ZvcmVncm91
								bmRDb2xvctIy
								Mz0+XxATTlNN
								dXRhYmxlRGlj
								dGlvbmFyeaM9
								PzdcTlNEaWN0
								aW9uYXJ50xgR
								C0FEH6IaG4AF
								gAaiRUaADoAP
								gAxXezAsIDI3
								fd8QD0pLTE1O
								C09QUVJTVFVW
								V1hZWltcXV5f
								YGFiY2RlZl8Q
								EW1heGltdW1M
								aW5lSGVpZ2h0
								WHRhYlN0b3Bz
								XxAQcGFyYWdy
								YXBoU3BhY2lu
								Z1poZWFkSW5k
								ZW50XWxpbmVC
								cmVha01vZGVb
								bGluZVNwYWNp
								bmdZYWxpZ25t
								ZW50WnRhaWxJ
								bmRlbnRfEBFt
								aW5pbXVtTGlu
								ZUhlaWdodF8Q
								FnBhcmFncmFw
								aFNwYWNpbmdC
								ZWZvcmVfEBJk
								ZWZhdWx0VGFi
								SW50ZXJ2YWxf
								EBJmaXJzdExp
								bmVIZWFkSWRl
								bnRfEBRiYXNl
								V3JpdGluZ0Rp
								cmVjdGlvbl8Q
								EmxpbmVIZWln
								aHRNdWx0aXBs
								ZSIAAAAAgBAi
								AAAAACIAAAAA
								gBKAIiIAAAAA
								gCAiAAAAACIA
								AAAAIgAAAAAi
								AAAAACIAAAAA
								gCEiAAAAANIR
								C2gWrGlqa2xt
								bm9wcXJzdIAR
								gBSAFYAWgBeA
								GIAZgBqAG4Ac
								gB2AHoAf1FB3
								eAtcent8V29w
								dGlvbnNYbG9j
								YXRpb26AEoAA
								IkHgAACAExAA
								0jIzf4BbTU5B
								U1RleHRUYWKi
								gTdbTU5BU1Rl
								eHRUYWLUUHd4
								C1x6hXyAEoAA
								IkJgAACAE9RQ
								d3gLXHqKfIAS
								gAAiQqgAAIAT
								1FB3eAtceo98
								gBKAACJC4AAA
								gBPUUHd4C1x6
								lHyAEoAAIkMM
								AACAE9RQd3gL
								XHqZfIASgAAi
								QygAAIAT1FB3
								eAtcep58gBKA
								ACJDRAAAgBPU
								UHd4C1x6o3yA
								EoAAIkNgAACA
								E9RQd3gLXHqo
								fIASgAAiQ3wA
								AIAT1FB3eAtc
								eq18gBKAACJD
								jAAAgBPUUHd4
								C1x6snyAEoAA
								IkOaAACAE9RQ
								d3gLXHq3fIAS
								gAAiQ6gAAIAT
								0jIzurtXTlNB
								cnJheaK6NxAE
								FAAAAAAAAAAA
								///////////S
								MjO/wF8QE01O
								QVNQYXJhZ3Jh
								cGh5U3R5bGWi
								wTdfEBNNTkFT
								UGFyYWdyYXBo
								eVN0eWxl0xgR
								C8PGH6IaG4AF
								gAaix8iAJIAl
								gAxXezAsIDI3
								fdbMzc7P0AvR
								0tPU1dZUc2l6
								ZVhmb250TmFt
								ZVlleHBhbnNp
								b25bb2JsaXF1
								ZW5lc3NfEBJi
								YXNlbGluZUFk
								anVzdG1lbnSA
								J4AmgCqAKYAo
								gCtcTHVjaWRh
								R3JhbmRlIkFA
								AAAiAAAAACIA
								AAAAIgAAAADS
								MjPd3lhNTkFT
								Rm9udKLfN1hN
								TkFTRm9udNIy
								M+HiXxATTU5D
								QXR0cmlidXRl
								ZFN0cmluZ6Lj
								N18QE01OQ0F0
								dHJpYnV0ZWRT
								dHJpbmdfEA9O
								U0tleWVkQXJj
								aGl2ZXLR5udf
								EBFNTkMwZGVy
								Um9vdE9iamVj
								dIABAAgAEQAa
								ACMALQAyADcA
								ZwBtAHQAewCG
								AI0AjwCRAJMA
								sQC2AMEAxQDH
								AMkAywDNANQA
								3ADfAOEA4wDm
								AOgA6gDsARMB
								PgFGAUsBUQFT
								AVUBYAFkAWoB
								bwF1AXcBfAGB
								AYYBiwGQAZsB
								pAGtAbABuQHC
								AccB3QHgAfYB
								+wIRAhUCIgIp
								AiwCLgIwAjMC
								NQI3AjkCQQJi
								AnYCfwKSAp0C
								qwK3AsECzALg
								AvkDDgMjAzoD
								TwNUA1YDWwNg
								A2IDZANpA2sD
								cAN1A3oDfwOE
								A4YDiwOQA50D
								nwOhA6MDpQOn
								A6kDqwOtA68D
								sQOzA7UDtwPA
								A8gD0QPTA9UD
								2gPcA94D4wPv
								A/ID/gQHBAkE
								CwQQBBIEGwQd
								BB8EJAQmBC8E
								MQQzBDgEOgRD
								BEUERwRMBE4E
								VwRZBFsEYARi
								BGsEbQRvBHQE
								dgR/BIEEgwSI
								BIoEkwSVBJcE
								nASeBKcEqQSr
								BLAEsgS7BL0E
								vwTEBMYEzwTR
								BNME2ATaBN8E
								5wTqBOwE/QUC
								BRgFGwUxBTgF
								OwU9BT8FQgVE
								BUYFSAVQBV0F
								YgVrBXUFgQWW
								BZgFmgWcBZ4F
								oAWiBa8FtAW5
								Bb4FwwXIBdEF
								1AXdBeIF+AX7
								BhEGIwYmBjoA
								AAAAAAACAQAA
								AAAAAADoAAAA
								AAAAAAAAAAAA
								AAAGPA==
									</data>
									<key>constrainedWidth</key>
									<integer>300</integer>
									<key>shrinkToFitContent</key>
									<integer>1</integer>
									<key>text</key>
									<string>{\rtf1\ansi\ansicpg1252\cocoartf1187
{\fonttbl\f0\fnil\fcharset0 LucidaGrande;}
{\colortbl;\red255\green255\blue255;}
\pard\tx560\tx1120\tx1680\tx2240\tx2800\tx3360\tx3920\tx4480\tx5040\tx5600\tx6160\tx6720\pardirnatural

\f0\fs24 \cf0 Contoller::PlayInitSequence}</string>
								</dict>
							</dict>
						</array>
						<key>title</key>
						<dict>
							<key>attributedText</key>
							<data>
							YnBsaXN0MDDUAQIDBAUG
							5OVYJHZlcnNpb25YJG9i
							amVjdHNZJGFyY2hpdmVy
							VCR0b3ASAAGGoK8QLQcI
							DxAXICEiIycxODxASEln
							dn1+goeMkZaboKWqr7S5
							vL2+wsrL19jZ2tvc4FUk
							bnVsbNMJCgsMDQ5Wc3Ry
							aW5nWmF0dHJpYnV0ZXNW
							JGNsYXNzgAKAA4AsXERy
							aXZlcjo6SW5pdNIRCxIW
							Wk5TLm9iamVjdHOjExQV
							gASADYAjgB/TGBELGRwf
							V05TLmtleXOiGhuABYAG
							oh0egAeACIAMXxAka01O
							QXR0cmlidXRlZFN0cmlu
							Z0F0dHJpYnV0ZVJhbmdl
							S2V5XxAoa01OQXR0cmli
							dXRlZFN0cmluZ0F0dHJp
							YnV0ZUF0dHJpYnV0ZUtl
							eVd7MCwgMTJ90iQLJSZV
							Y29sb3KACYAL1QsoKSor
							LC0uLzBTcmVkVWFscGhh
							VGJsdWVVZ3JlZW6ACiIA
							AAAAIj+AAAAiAAAAACIA
							AAAA0jIzNDVaJGNsYXNz
							bmFtZVgkY2xhc3Nlc1hN
							TkNDb2xvcqI2N1hNTkND
							b2xvclhOU09iamVjdNIy
							Mzk6XxATTU5BU0ZvcmVn
							cm91bmRDb2xvcqI7N18Q
							E01OQVNGb3JlZ3JvdW5k
							Q29sb3LSMjM9Pl8QE05T
							TXV0YWJsZURpY3Rpb25h
							cnmjPT83XE5TRGljdGlv
							bmFyedMYEQtBRB+iGhuA
							BYAGokVGgA6AD4AMV3sw
							LCAxMn3fEA9KS0xNTgtP
							UFFSU1RVVldYWVpbXF1e
							X2BhYmNkZWZfEBFtYXhp
							bXVtTGluZUhlaWdodFh0
							YWJTdG9wc18QEHBhcmFn
							cmFwaFNwYWNpbmdaaGVh
							ZEluZGVudF1saW5lQnJl
							YWtNb2RlW2xpbmVTcGFj
							aW5nWWFsaWdubWVudFp0
							YWlsSW5kZW50XxARbWlu
							aW11bUxpbmVIZWlnaHRf
							EBZwYXJhZ3JhcGhTcGFj
							aW5nQmVmb3JlXxASZGVm
							YXVsdFRhYkludGVydmFs
							XxASZmlyc3RMaW5lSGVh
							ZElkZW50XxAUYmFzZVdy
							aXRpbmdEaXJlY3Rpb25f
							EBJsaW5lSGVpZ2h0TXVs
							dGlwbGUiAAAAAIAQIgAA
							AAAiAAAAAIASgCIiAAAA
							AIAgIgAAAAAiAAAAACIA
							AAAAIgAAAAAiAAAAAIAh
							IgAAAADSEQtoFqxpamts
							bW5vcHFyc3SAEYAUgBWA
							FoAXgBiAGYAagBuAHIAd
							gB6AH9RQd3gLXHp7fFdv
							cHRpb25zWGxvY2F0aW9u
							gBKAACJB4AAAgBMQANIy
							M3+AW01OQVNUZXh0VGFi
							ooE3W01OQVNUZXh0VGFi
							1FB3eAtceoV8gBKAACJC
							YAAAgBPUUHd4C1x6inyA
							EoAAIkKoAACAE9RQd3gL
							XHqPfIASgAAiQuAAAIAT
							1FB3eAtcepR8gBKAACJD
							DAAAgBPUUHd4C1x6mXyA
							EoAAIkMoAACAE9RQd3gL
							XHqefIASgAAiQ0QAAIAT
							1FB3eAtceqN8gBKAACJD
							YAAAgBPUUHd4C1x6qHyA
							EoAAIkN8AACAE9RQd3gL
							XHqtfIASgAAiQ4wAAIAT
							1FB3eAtcerJ8gBKAACJD
							mgAAgBPUUHd4C1x6t3yA
							EoAAIkOoAACAE9IyM7q7
							V05TQXJyYXmiujcQBBQA
							AAAAAAAAAP//////////
							0jIzv8BfEBNNTkFTUGFy
							YWdyYXBoeVN0eWxlosE3
							XxATTU5BU1BhcmFncmFw
							aHlTdHlsZdMYEQvDxh+i
							GhuABYAGosfIgCSAJYAM
							V3swLCAxMn3WzM3Oz9AL
							0dLT1NXWVHNpemVYZm9u
							dE5hbWVZZXhwYW5zaW9u
							W29ibGlxdWVuZXNzXxAS
							YmFzZWxpbmVBZGp1c3Rt
							ZW50gCeAJoAqgCmAKIAr
							XEx1Y2lkYUdyYW5kZSJB
							QAAAIgAAAAAiAAAAACIA
							AAAA0jIz3d5YTU5BU0Zv
							bnSi3zdYTU5BU0ZvbnTS
							MjPh4l8QE01OQ0F0dHJp
							YnV0ZWRTdHJpbmei4zdf
							EBNNTkNBdHRyaWJ1dGVk
							U3RyaW5nXxAPTlNLZXll
							ZEFyY2hpdmVy0ebnXxAR
							TU5DMGRlclJvb3RPYmpl
							Y3SAAQAIABEAGgAjAC0A
							MgA3AGcAbQB0AHsAhgCN
							AI8AkQCTAKAApQCwALQA
							tgC4ALoAvADDAMsAzgDQ
							ANIA1QDXANkA2wECAS0B
							NQE6AUABQgFEAU8BUwFZ
							AV4BZAFmAWsBcAF1AXoB
							fwGKAZMBnAGfAagBsQG2
							AcwBzwHlAeoCAAIEAhEC
							GAIbAh0CHwIiAiQCJgIo
							AjACUQJlAm4CgQKMApoC
							pgKwArsCzwLoAv0DEgMp
							Az4DQwNFA0oDTwNRA1MD
							WANaA18DZANpA24DcwN1
							A3oDfwOMA44DkAOSA5QD
							lgOYA5oDnAOeA6ADogOk
							A6YDrwO3A8ADwgPEA8kD
							ywPNA9ID3gPhA+0D9gP4
							A/oD/wQBBAoEDAQOBBME
							FQQeBCAEIgQnBCkEMgQ0
							BDYEOwQ9BEYESARKBE8E
							UQRaBFwEXgRjBGUEbgRw
							BHIEdwR5BIIEhASGBIsE
							jQSWBJgEmgSfBKEEqgSs
							BK4EswS1BL4EwATCBMcE
							yQTOBNYE2QTbBOwE8QUH
							BQoFIAUnBSoFLAUuBTEF
							MwU1BTcFPwVMBVEFWgVk
							BXAFhQWHBYkFiwWNBY8F
							kQWeBaMFqAWtBbIFtwXA
							BcMFzAXRBecF6gYABhIG
							FQYpAAAAAAAAAgEAAAAA
							AAAA6AAAAAAAAAAAAAAA
							AAAABis=
							</data>
							<key>constrainedWidth</key>
							<integer>300</integer>
							<key>shrinkToFitContent</key>
							<integer>1</integer>
							<key>text</key>
							<string>{\rtf1\ansi\ansicpg1252\cocoartf1187
{\fonttbl\f0\fnil\fcharset0 LucidaGrande;}
{\colortbl;\red255\green255\blue255;}
\pard\tx560\tx1120\tx1680\tx2240\tx2800\tx3360\tx3920\tx4480\tx5040\tx5600\tx6160\tx6720\pardirnatural

\f0\fs24 \cf0 Driver::Init}</string>
						</dict>
					</dict>
				</array>
				<key>title</key>
				<dict>
					<key>attributedText</key>
					<data>
					YnBsaXN0MDDUAQIDBAUG4+RYJHZlcnNpb25Y
					JG9iamVjdHNZJGFyY2hpdmVyVCR0b3ASAAGG
					oK8QLAcIDxAXICEiIycxODxASElndn1+goeM
					kZaboKWqr7S5vL3BycrW19jZ2tvfVSRudWxs
					0wkKCwwNDlZzdHJpbmdaYXR0cmlidXRlc1Yk
					Y2xhc3OAAoADgCtfEA96LXdhdmUgcHJvdG9j
					b2zSEQsSFlpOUy5vYmplY3RzoxMUFYAEgA2A
					IoAf0xgRCxkcH1dOUy5rZXlzohobgAWABqId
					HoAHgAiADF8QJGtNTkF0dHJpYnV0ZWRTdHJp
					bmdBdHRyaWJ1dGVSYW5nZUtleV8QKGtNTkF0
					dHJpYnV0ZWRTdHJpbmdBdHRyaWJ1dGVBdHRy
					aWJ1dGVLZXlXezAsIDE1fdIkCyUmVWNvbG9y
					gAmAC9ULKCkqKywtLi8wU3JlZFVhbHBoYVRi
					bHVlVWdyZWVugAoiAAAAACI/gAAAIgAAAAAi
					AAAAANIyMzQ1WiRjbGFzc25hbWVYJGNsYXNz
					ZXNYTU5DQ29sb3KiNjdYTU5DQ29sb3JYTlNP
					YmplY3TSMjM5Ol8QE01OQVNGb3JlZ3JvdW5k
					Q29sb3KiOzdfEBNNTkFTRm9yZWdyb3VuZENv
					bG9y0jIzPT5fEBNOU011dGFibGVEaWN0aW9u
					YXJ5oz0/N1xOU0RpY3Rpb25hcnnTGBELQUQf
					ohobgAWABqJFRoAOgA+ADFd7MCwgMTV93xAP
					SktMTU4LT1BRUlNUVVZXWFlaW1xdXlxgYWJj
					ZGVmXxARbWF4aW11bUxpbmVIZWlnaHRYdGFi
					U3RvcHNfEBBwYXJhZ3JhcGhTcGFjaW5nWmhl
					YWRJbmRlbnRdbGluZUJyZWFrTW9kZVtsaW5l
					U3BhY2luZ1lhbGlnbm1lbnRadGFpbEluZGVu
					dF8QEW1pbmltdW1MaW5lSGVpZ2h0XxAWcGFy
					YWdyYXBoU3BhY2luZ0JlZm9yZV8QEmRlZmF1
					bHRUYWJJbnRlcnZhbF8QEmZpcnN0TGluZUhl
					YWRJZGVudF8QFGJhc2VXcml0aW5nRGlyZWN0
					aW9uXxASbGluZUhlaWdodE11bHRpcGxlIgAA
					AACAECIAAAAAIgAAAACAEoAhIgAAAACAEiIA
					AAAAIgAAAAAiAAAAACIAAAAAIgAAAACAICIA
					AAAA0hELaBasaWprbG1ub3BxcnN0gBGAFIAV
					gBaAF4AYgBmAGoAbgByAHYAegB/UUHd4C1x6
					e3xXb3B0aW9uc1hsb2NhdGlvboASgAAiQeAA
					AIATEADSMjN/gFtNTkFTVGV4dFRhYqKBN1tN
					TkFTVGV4dFRhYtRQd3gLXHqFfIASgAAiQmAA
					AIAT1FB3eAtceop8gBKAACJCqAAAgBPUUHd4
					C1x6j3yAEoAAIkLgAACAE9RQd3gLXHqUfIAS
					gAAiQwwAAIAT1FB3eAtcepl8gBKAACJDKAAA
					gBPUUHd4C1x6nnyAEoAAIkNEAACAE9RQd3gL
					XHqjfIASgAAiQ2AAAIAT1FB3eAtceqh8gBKA
					ACJDfAAAgBPUUHd4C1x6rXyAEoAAIkOMAACA
					E9RQd3gLXHqyfIASgAAiQ5oAAIAT1FB3eAtc
					erd8gBKAACJDqAAAgBPSMjO6u1dOU0FycmF5
					oro3FAAAAAAAAAAA///////////SMjO+v18Q
					E01OQVNQYXJhZ3JhcGh5U3R5bGWiwDdfEBNN
					TkFTUGFyYWdyYXBoeVN0eWxl0xgRC8LFH6Ia
					G4AFgAaixseAI4AkgAxXezAsIDE1fdbLzM3O
					zwvQ0dLT1NVUc2l6ZVhmb250TmFtZVlleHBh
					bnNpb25bb2JsaXF1ZW5lc3NfEBJiYXNlbGlu
					ZUFkanVzdG1lbnSAJoAlgCmAKIAngCpcTHVj
					aWRhR3JhbmRlIkEQAAAiAAAAACIAAAAAIgAA
					AADSMjPc3VhNTkFTRm9udKLeN1hNTkFTRm9u
					dNIyM+DhXxATTU5DQXR0cmlidXRlZFN0cmlu
					Z6LiN18QE01OQ0F0dHJpYnV0ZWRTdHJpbmdf
					EA9OU0tleWVkQXJjaGl2ZXLR5eZfEBFNTkMw
					ZGVyUm9vdE9iamVjdIABAAgAEQAaACMALQAy
					ADcAZgBsAHMAegCFAIwAjgCQAJIApACpALQA
					uAC6ALwAvgDAAMcAzwDSANQA1gDZANsA3QDf
					AQYBMQE5AT4BRAFGAUgBUwFXAV0BYgFoAWoB
					bwF0AXkBfgGDAY4BlwGgAaMBrAG1AboB0AHT
					AekB7gIEAggCFQIcAh8CIQIjAiYCKAIqAiwC
					NAJVAmkCcgKFApACngKqArQCvwLTAuwDAQMW
					Ay0DQgNHA0kDTgNTA1UDVwNcA14DYwNoA20D
					cgN3A3kDfgODA5ADkgOUA5YDmAOaA5wDngOg
					A6IDpAOmA6gDqgOzA7sDxAPGA8gDzQPPA9ED
					1gPiA+UD8QP6A/wD/gQDBAUEDgQQBBIEFwQZ
					BCIEJAQmBCsELQQ2BDgEOgQ/BEEESgRMBE4E
					UwRVBF4EYARiBGcEaQRyBHQEdgR7BH0EhgSI
					BIoEjwSRBJoEnASeBKMEpQSuBLAEsgS3BLkE
					wgTEBMYEywTNBNIE2gTdBO4E8wUJBQwFIgUp
					BSwFLgUwBTMFNQU3BTkFQQVOBVMFXAVmBXIF
					hwWJBYsFjQWPBZEFkwWgBaUFqgWvBbQFuQXC
					BcUFzgXTBekF7AYCBhQGFwYrAAAAAAAAAgEA
					AAAAAAAA5wAAAAAAAAAAAAAAAAAABi0=
					</data>
					<key>constrainedWidth</key>
					<integer>300</integer>
					<key>shrinkToFitContent</key>
					<integer>1</integer>
					<key>text</key>
					<string>{\rtf1\ansi\ansicpg1252\cocoartf1187
{\fonttbl\f0\fnil\fcharset0 LucidaGrande;}
{\colortbl;\red255\green255\blue255;}
\pard\tx560\tx1120\tx1680\tx2240\tx2800\tx3360\tx3920\tx4480\tx5040\tx5600\tx6160\tx6720\pardirnatural

\f0\fs18 \cf0 z-wave protocol}</string>
				</dict>
			</dict>
		</array>
	</dict>
	<key>printInfo</key>
	<data>
	BAtzdHJlYW10eXBlZIHoA4QBQISEhAtOU1ByaW50SW5mbwGEhAhOU09iamVjdACFkoSE
	hBNOU011dGFibGVEaWN0aW9uYXJ5AISEDE5TRGljdGlvbmFyeQCUhAFpCJKEhIQITlNT
	dHJpbmcBlIQBKxZOU0hvcml6b250YWxseUNlbnRlcmVkhpKEhIQITlNOdW1iZXIAhIQH
	TlNWYWx1ZQCUhAEqhIQBY50BhpKEmZkNTlNSaWdodE1hcmdpboaShJuchIQBZp5IhpKE
	mZkMTlNMZWZ0TWFyZ2luhpKEm5ygnkiGkoSZmRVOU0hvcml6b25hbFBhZ2luYXRpb26G
	koSbnISXlwKGkoSZmRROU1ZlcnRpY2FsUGFnaW5hdGlvboaShJucpZcAhpKEmZkUTlNW
	ZXJ0aWNhbGx5Q2VudGVyZWSGkpqShJmZC05TVG9wTWFyZ2luhpKEm5ygnlqGkoSZmQ5O
	U0JvdHRvbU1hcmdpboaShJucoJ5ahoaG
	</data>
	<key>title</key>
	<string>z-wave protocol</string>
	<key>version</key>
	<integer>4</integer>
</dict>
</plist>
